{
  "slug": "crispy-fatty-brazilian-gherkin-delight-bites",
  "title": "Crispy Gherkin Bites",
  "description": "A delightful, crispy snack perfect for any occasion. The addition of gherkin adds a tangy twist.",
  "cuisine": "Brazilian",
  "diet": [
    "vegetarian",
    "gluten-free"
  ],
  "meal": "snack",
  "ingredients": [
    {
      "name": "Bites",
      "amount": "250g",
      "notes": "Your favorite snack bite crackers"
    },
    {
      "name": "Gherkin",
      "amount": "1/2 cup",
      "notes": "Finely chopped"
    },
    {
      "name": "Crispy",
      "amount": "1/4 cup",
      "notes": "Crushed crispy snack"
    },
    {
      "name": "Delight",
      "amount": "2 tbsp",
      "notes": "Your favorite seasonings"
    }
  ],
  "instructions": [
    "Preheat the oven to 375°F (190°C).",
    "Line a baking sheet with parchment paper.",
    "Place the bite crackers on the prepared baking sheet.",
    "In a bowl, mix together gherkin, crispy, and delight.",
    "Sprinkle the mixture evenly over the crackers.",
    "Bake for 10-12 minutes or until the crackers are golden brown.",
    "Remove from the oven and let cool completely.",
    "Serve and enjoy!"
  ],
  "prepTimeMin": 5,
  "cookTimeMin": 12,
  "totalTimeMin": 17,
  "servings": 10,
  "difficulty": "easy",
  "tags": [
    "snack",
    "easy",
    "quick"
  ],
  "source": "foodrecipes.page",
  "canonicalUrl": "https://foodrecipes.page/recipe/crispy-fatty-brazilian-gherkin-delight-bites",
  "providerUsed": "groq",
  "createdAt": "2026-06-10T22:00:15.247Z"
}